dupr/__init__.py
dupr/auth.py
dupr/exceptions.py
dupr/http_client.py
dupr-0.2.1.dist-info/LICENSE
dupr-0.2.1.dist-info/METADATA
dupr-0.2.1.dist-info/WHEEL
dupr-0.2.1.dist-info/RECORD
